<?xml version="1.0" encoding="UTF-8"?>
<?xml-stylesheet href="CoreNLP-to-HTML.xsl" type="text/xsl"?>
<root>
  <document>
    <sentences>
      <sentence id="1">
        <tokens>
          <token id="1">
            <word>``</word>
            <lemma>``</lemma>
            <CharacterOffsetBegin>0</CharacterOffsetBegin>
            <CharacterOffsetEnd>1</CharacterOffsetEnd>
            <POS>``</POS>
            <NER>O</NER>
          </token>
          <token id="2">
            <word>WEST</word>
            <lemma>west</lemma>
            <CharacterOffsetBegin>1</CharacterOffsetBegin>
            <CharacterOffsetEnd>5</CharacterOffsetEnd>
            <POS>NN</POS>
            <NER>O</NER>
            <Speaker>PER1</Speaker>
          </token>
          <token id="3">
            <word>POINT</word>
            <lemma>point</lemma>
            <CharacterOffsetBegin>6</CharacterOffsetBegin>
            <CharacterOffsetEnd>11</CharacterOffsetEnd>
            <POS>NN</POS>
            <NER>O</NER>
            <Speaker>PER1</Speaker>
          </token>
          <token id="4">
            <word>N.Y.</word>
            <lemma>N.Y.</lemma>
            <CharacterOffsetBegin>12</CharacterOffsetBegin>
            <CharacterOffsetEnd>16</CharacterOffsetEnd>
            <POS>NNP</POS>
            <NER>LOCATION</NER>
            <Speaker>PER1</Speaker>
          </token>
          <token id="5">
            <word>-LRB-</word>
            <lemma>-lrb-</lemma>
            <CharacterOffsetBegin>17</CharacterOffsetBegin>
            <CharacterOffsetEnd>18</CharacterOffsetEnd>
            <POS>-LRB-</POS>
            <NER>O</NER>
            <Speaker>PER1</Speaker>
          </token>
          <token id="6">
            <word>Reuters</word>
            <lemma>Reuters</lemma>
            <CharacterOffsetBegin>18</CharacterOffsetBegin>
            <CharacterOffsetEnd>25</CharacterOffsetEnd>
            <POS>NNP</POS>
            <NER>ORGANIZATION</NER>
            <Speaker>PER1</Speaker>
          </token>
          <token id="7">
            <word>-RRB-</word>
            <lemma>-rrb-</lemma>
            <CharacterOffsetBegin>25</CharacterOffsetBegin>
            <CharacterOffsetEnd>26</CharacterOffsetEnd>
            <POS>-RRB-</POS>
            <NER>O</NER>
            <Speaker>PER1</Speaker>
          </token>
          <token id="8">
            <word>-</word>
            <lemma>-</lemma>
            <CharacterOffsetBegin>27</CharacterOffsetBegin>
            <CharacterOffsetEnd>28</CharacterOffsetEnd>
            <POS>:</POS>
            <NER>O</NER>
            <Speaker>PER1</Speaker>
          </token>
          <token id="9">
            <word>In</word>
            <lemma>in</lemma>
            <CharacterOffsetBegin>29</CharacterOffsetBegin>
            <CharacterOffsetEnd>31</CharacterOffsetEnd>
            <POS>IN</POS>
            <NER>O</NER>
            <Speaker>PER1</Speaker>
          </token>
          <token id="10">
            <word>a</word>
            <lemma>a</lemma>
            <CharacterOffsetBegin>32</CharacterOffsetBegin>
            <CharacterOffsetEnd>33</CharacterOffsetEnd>
            <POS>DT</POS>
            <NER>O</NER>
            <Speaker>PER1</Speaker>
          </token>
          <token id="11">
            <word>major</word>
            <lemma>major</lemma>
            <CharacterOffsetBegin>34</CharacterOffsetBegin>
            <CharacterOffsetEnd>39</CharacterOffsetEnd>
            <POS>JJ</POS>
            <NER>O</NER>
            <Speaker>PER1</Speaker>
          </token>
          <token id="12">
            <word>foreign</word>
            <lemma>foreign</lemma>
            <CharacterOffsetBegin>40</CharacterOffsetBegin>
            <CharacterOffsetEnd>47</CharacterOffsetEnd>
            <POS>JJ</POS>
            <NER>O</NER>
            <Speaker>PER1</Speaker>
          </token>
          <token id="13">
            <word>policy</word>
            <lemma>policy</lemma>
            <CharacterOffsetBegin>48</CharacterOffsetBegin>
            <CharacterOffsetEnd>54</CharacterOffsetEnd>
            <POS>NN</POS>
            <NER>O</NER>
            <Speaker>PER1</Speaker>
          </token>
          <token id="14">
            <word>address</word>
            <lemma>address</lemma>
            <CharacterOffsetBegin>55</CharacterOffsetBegin>
            <CharacterOffsetEnd>62</CharacterOffsetEnd>
            <POS>NN</POS>
            <NER>O</NER>
            <Speaker>PER1</Speaker>
          </token>
          <token id="15">
            <word>on</word>
            <lemma>on</lemma>
            <CharacterOffsetBegin>63</CharacterOffsetBegin>
            <CharacterOffsetEnd>65</CharacterOffsetEnd>
            <POS>IN</POS>
            <NER>O</NER>
            <Speaker>PER1</Speaker>
          </token>
          <token id="16">
            <word>Wednesday</word>
            <lemma>Wednesday</lemma>
            <CharacterOffsetBegin>66</CharacterOffsetBegin>
            <CharacterOffsetEnd>75</CharacterOffsetEnd>
            <POS>NNP</POS>
            <NER>DATE</NER>
            <NormalizedNER>XXXX-WXX-3</NormalizedNER>
            <Speaker>PER1</Speaker>
            <Timex tid="t1" type="DATE">XXXX-WXX-3</Timex>
          </token>
          <token id="17">
            <word>,</word>
            <lemma>,</lemma>
            <CharacterOffsetBegin>75</CharacterOffsetBegin>
            <CharacterOffsetEnd>76</CharacterOffsetEnd>
            <POS>,</POS>
            <NER>O</NER>
            <Speaker>PER1</Speaker>
          </token>
          <token id="18">
            <word>President</word>
            <lemma>President</lemma>
            <CharacterOffsetBegin>77</CharacterOffsetBegin>
            <CharacterOffsetEnd>86</CharacterOffsetEnd>
            <POS>NNP</POS>
            <NER>O</NER>
            <Speaker>PER1</Speaker>
          </token>
          <token id="19">
            <word>Barack</word>
            <lemma>Barack</lemma>
            <CharacterOffsetBegin>87</CharacterOffsetBegin>
            <CharacterOffsetEnd>93</CharacterOffsetEnd>
            <POS>NNP</POS>
            <NER>PERSON</NER>
            <Speaker>PER1</Speaker>
          </token>
          <token id="20">
            <word>Obama</word>
            <lemma>Obama</lemma>
            <CharacterOffsetBegin>94</CharacterOffsetBegin>
            <CharacterOffsetEnd>99</CharacterOffsetEnd>
            <POS>NNP</POS>
            <NER>PERSON</NER>
            <Speaker>PER1</Speaker>
          </token>
          <token id="21">
            <word>said</word>
            <lemma>say</lemma>
            <CharacterOffsetBegin>100</CharacterOffsetBegin>
            <CharacterOffsetEnd>104</CharacterOffsetEnd>
            <POS>VBD</POS>
            <NER>O</NER>
            <Speaker>PER1</Speaker>
          </token>
          <token id="22">
            <word>he</word>
            <lemma>he</lemma>
            <CharacterOffsetBegin>105</CharacterOffsetBegin>
            <CharacterOffsetEnd>107</CharacterOffsetEnd>
            <POS>PRP</POS>
            <NER>O</NER>
            <Speaker>PER1</Speaker>
          </token>
          <token id="23">
            <word>will</word>
            <lemma>will</lemma>
            <CharacterOffsetBegin>108</CharacterOffsetBegin>
            <CharacterOffsetEnd>112</CharacterOffsetEnd>
            <POS>MD</POS>
            <NER>O</NER>
            <Speaker>PER1</Speaker>
          </token>
          <token id="24">
            <word>work</word>
            <lemma>work</lemma>
            <CharacterOffsetBegin>113</CharacterOffsetBegin>
            <CharacterOffsetEnd>117</CharacterOffsetEnd>
            <POS>VB</POS>
            <NER>O</NER>
            <Speaker>PER1</Speaker>
          </token>
          <token id="25">
            <word>with</word>
            <lemma>with</lemma>
            <CharacterOffsetBegin>118</CharacterOffsetBegin>
            <CharacterOffsetEnd>122</CharacterOffsetEnd>
            <POS>IN</POS>
            <NER>O</NER>
            <Speaker>PER1</Speaker>
          </token>
          <token id="26">
            <word>Congress</word>
            <lemma>Congress</lemma>
            <CharacterOffsetBegin>123</CharacterOffsetBegin>
            <CharacterOffsetEnd>131</CharacterOffsetEnd>
            <POS>NNP</POS>
            <NER>ORGANIZATION</NER>
            <Speaker>PER1</Speaker>
          </token>
          <token id="27">
            <word>to</word>
            <lemma>to</lemma>
            <CharacterOffsetBegin>132</CharacterOffsetBegin>
            <CharacterOffsetEnd>134</CharacterOffsetEnd>
            <POS>TO</POS>
            <NER>O</NER>
            <Speaker>PER1</Speaker>
          </token>
          <token id="28">
            <word>ramp</word>
            <lemma>ramp</lemma>
            <CharacterOffsetBegin>135</CharacterOffsetBegin>
            <CharacterOffsetEnd>139</CharacterOffsetEnd>
            <POS>NN</POS>
            <NER>O</NER>
            <Speaker>PER1</Speaker>
          </token>
          <token id="29">
            <word>up</word>
            <lemma>up</lemma>
            <CharacterOffsetBegin>140</CharacterOffsetBegin>
            <CharacterOffsetEnd>142</CharacterOffsetEnd>
            <POS>RP</POS>
            <NER>O</NER>
            <Speaker>PER1</Speaker>
          </token>
          <token id="30">
            <word>U.S.</word>
            <lemma>U.S.</lemma>
            <CharacterOffsetBegin>143</CharacterOffsetBegin>
            <CharacterOffsetEnd>147</CharacterOffsetEnd>
            <POS>NNP</POS>
            <NER>LOCATION</NER>
            <Speaker>PER1</Speaker>
          </token>
          <token id="31">
            <word>support</word>
            <lemma>support</lemma>
            <CharacterOffsetBegin>148</CharacterOffsetBegin>
            <CharacterOffsetEnd>155</CharacterOffsetEnd>
            <POS>NN</POS>
            <NER>O</NER>
            <Speaker>PER1</Speaker>
          </token>
          <token id="32">
            <word>for</word>
            <lemma>for</lemma>
            <CharacterOffsetBegin>156</CharacterOffsetBegin>
            <CharacterOffsetEnd>159</CharacterOffsetEnd>
            <POS>IN</POS>
            <NER>O</NER>
            <Speaker>PER1</Speaker>
          </token>
          <token id="33">
            <word>Syrian</word>
            <lemma>syrian</lemma>
            <CharacterOffsetBegin>160</CharacterOffsetBegin>
            <CharacterOffsetEnd>166</CharacterOffsetEnd>
            <POS>JJ</POS>
            <NER>MISC</NER>
            <Speaker>PER1</Speaker>
          </token>
          <token id="34">
            <word>opposition</word>
            <lemma>opposition</lemma>
            <CharacterOffsetBegin>167</CharacterOffsetBegin>
            <CharacterOffsetEnd>177</CharacterOffsetEnd>
            <POS>NN</POS>
            <NER>O</NER>
            <Speaker>PER1</Speaker>
          </token>
          <token id="35">
            <word>groups</word>
            <lemma>group</lemma>
            <CharacterOffsetBegin>178</CharacterOffsetBegin>
            <CharacterOffsetEnd>184</CharacterOffsetEnd>
            <POS>NNS</POS>
            <NER>O</NER>
            <Speaker>PER1</Speaker>
          </token>
          <token id="36">
            <word>that</word>
            <lemma>that</lemma>
            <CharacterOffsetBegin>185</CharacterOffsetBegin>
            <CharacterOffsetEnd>189</CharacterOffsetEnd>
            <POS>WDT</POS>
            <NER>O</NER>
            <Speaker>PER1</Speaker>
          </token>
          <token id="37">
            <word>are</word>
            <lemma>be</lemma>
            <CharacterOffsetBegin>190</CharacterOffsetBegin>
            <CharacterOffsetEnd>193</CharacterOffsetEnd>
            <POS>VBP</POS>
            <NER>O</NER>
            <Speaker>PER1</Speaker>
          </token>
          <token id="38">
            <word>the</word>
            <lemma>the</lemma>
            <CharacterOffsetBegin>194</CharacterOffsetBegin>
            <CharacterOffsetEnd>197</CharacterOffsetEnd>
            <POS>DT</POS>
            <NER>O</NER>
            <Speaker>PER1</Speaker>
          </token>
          <token id="39">
            <word>best</word>
            <lemma>best</lemma>
            <CharacterOffsetBegin>198</CharacterOffsetBegin>
            <CharacterOffsetEnd>202</CharacterOffsetEnd>
            <POS>JJS</POS>
            <NER>O</NER>
            <Speaker>PER1</Speaker>
          </token>
          <token id="40">
            <word>alternative</word>
            <lemma>alternative</lemma>
            <CharacterOffsetBegin>203</CharacterOffsetBegin>
            <CharacterOffsetEnd>214</CharacterOffsetEnd>
            <POS>NN</POS>
            <NER>O</NER>
            <Speaker>PER1</Speaker>
          </token>
          <token id="41">
            <word>to</word>
            <lemma>to</lemma>
            <CharacterOffsetBegin>215</CharacterOffsetBegin>
            <CharacterOffsetEnd>217</CharacterOffsetEnd>
            <POS>TO</POS>
            <NER>O</NER>
            <Speaker>PER1</Speaker>
          </token>
          <token id="42">
            <word>President</word>
            <lemma>President</lemma>
            <CharacterOffsetBegin>219</CharacterOffsetBegin>
            <CharacterOffsetEnd>228</CharacterOffsetEnd>
            <POS>NNP</POS>
            <NER>O</NER>
            <Speaker>PER1</Speaker>
          </token>
          <token id="43">
            <word>Bashar</word>
            <lemma>Bashar</lemma>
            <CharacterOffsetBegin>229</CharacterOffsetBegin>
            <CharacterOffsetEnd>235</CharacterOffsetEnd>
            <POS>NNP</POS>
            <NER>PERSON</NER>
            <Speaker>PER1</Speaker>
          </token>
          <token id="44">
            <word>al-Assad</word>
            <lemma>al-Assad</lemma>
            <CharacterOffsetBegin>236</CharacterOffsetBegin>
            <CharacterOffsetEnd>244</CharacterOffsetEnd>
            <POS>NNP</POS>
            <NER>PERSON</NER>
            <Speaker>PER1</Speaker>
          </token>
          <token id="45">
            <word>.</word>
            <lemma>.</lemma>
            <CharacterOffsetBegin>244</CharacterOffsetBegin>
            <CharacterOffsetEnd>245</CharacterOffsetEnd>
            <POS>.</POS>
            <NER>O</NER>
            <Speaker>PER1</Speaker>
          </token>
        </tokens>
        <parse>(ROOT (S (`` ``) (NP (NN WEST) (NN POINT) (NNP N.Y.) (-LRB- -LRB-) (NNP Reuters) (-RRB- -RRB-)) (PRN (: -) (PP (IN In) (NP (NP (DT a) (JJ major) (JJ foreign) (NN policy) (NN address)) (PP (IN on) (NP (NNP Wednesday)))))) (, ,) (NP (NNP President) (NNP Barack) (NNP Obama)) (VP (VBD said) (SBAR (S (NP (PRP he)) (VP (MD will) (VP (VB work) (PP (IN with) (NP (NNP Congress))) (S (VP (TO to) (VP (NN ramp) (PRT (RP up)) (NP (NP (NNP U.S.) (NN support)) (PP (IN for) (NP (JJ Syrian) (NN opposition) (NNS groups))) (SBAR (WHNP (WDT that)) (S (VP (VBP are) (NP (NP (DT the) (JJS best) (NN alternative)) (PP (TO to) (NP (NNP President) (NNP Bashar) (NNP al-Assad)))))))))))))))) (. .))) </parse>
        <dependencies type="basic-dependencies">
          <dep type="root">
            <governor idx="0">ROOT</governor>
            <dependent idx="21">said</dependent>
          </dep>
          <dep type="nn">
            <governor idx="6">Reuters</governor>
            <dependent idx="2">WEST</dependent>
          </dep>
          <dep type="nn">
            <governor idx="6">Reuters</governor>
            <dependent idx="3">POINT</dependent>
          </dep>
          <dep type="nn">
            <governor idx="6">Reuters</governor>
            <dependent idx="4">N.Y.</dependent>
          </dep>
          <dep type="nsubj">
            <governor idx="21">said</governor>
            <dependent idx="6">Reuters</dependent>
          </dep>
          <dep type="dep">
            <governor idx="21">said</governor>
            <dependent idx="9">In</dependent>
          </dep>
          <dep type="det">
            <governor idx="14">address</governor>
            <dependent idx="10">a</dependent>
          </dep>
          <dep type="amod">
            <governor idx="14">address</governor>
            <dependent idx="11">major</dependent>
          </dep>
          <dep type="amod">
            <governor idx="14">address</governor>
            <dependent idx="12">foreign</dependent>
          </dep>
          <dep type="nn">
            <governor idx="14">address</governor>
            <dependent idx="13">policy</dependent>
          </dep>
          <dep type="pobj">
            <governor idx="9">In</governor>
            <dependent idx="14">address</dependent>
          </dep>
          <dep type="prep">
            <governor idx="14">address</governor>
            <dependent idx="15">on</dependent>
          </dep>
          <dep type="pobj">
            <governor idx="15">on</governor>
            <dependent idx="16">Wednesday</dependent>
          </dep>
          <dep type="nn">
            <governor idx="20">Obama</governor>
            <dependent idx="18">President</dependent>
          </dep>
          <dep type="nn">
            <governor idx="20">Obama</governor>
            <dependent idx="19">Barack</dependent>
          </dep>
          <dep type="nsubj">
            <governor idx="21">said</governor>
            <dependent idx="20">Obama</dependent>
          </dep>
          <dep type="nsubj">
            <governor idx="24">work</governor>
            <dependent idx="22">he</dependent>
          </dep>
          <dep type="aux">
            <governor idx="24">work</governor>
            <dependent idx="23">will</dependent>
          </dep>
          <dep type="ccomp">
            <governor idx="21">said</governor>
            <dependent idx="24">work</dependent>
          </dep>
          <dep type="prep">
            <governor idx="24">work</governor>
            <dependent idx="25">with</dependent>
          </dep>
          <dep type="pobj">
            <governor idx="25">with</governor>
            <dependent idx="26">Congress</dependent>
          </dep>
          <dep type="aux">
            <governor idx="28">ramp</governor>
            <dependent idx="27">to</dependent>
          </dep>
          <dep type="xcomp">
            <governor idx="24">work</governor>
            <dependent idx="28">ramp</dependent>
          </dep>
          <dep type="prt">
            <governor idx="28">ramp</governor>
            <dependent idx="29">up</dependent>
          </dep>
          <dep type="nn">
            <governor idx="31">support</governor>
            <dependent idx="30">U.S.</dependent>
          </dep>
          <dep type="dobj">
            <governor idx="28">ramp</governor>
            <dependent idx="31">support</dependent>
          </dep>
          <dep type="prep">
            <governor idx="31">support</governor>
            <dependent idx="32">for</dependent>
          </dep>
          <dep type="amod">
            <governor idx="35">groups</governor>
            <dependent idx="33">Syrian</dependent>
          </dep>
          <dep type="nn">
            <governor idx="35">groups</governor>
            <dependent idx="34">opposition</dependent>
          </dep>
          <dep type="pobj">
            <governor idx="32">for</governor>
            <dependent idx="35">groups</dependent>
          </dep>
          <dep type="nsubj">
            <governor idx="40">alternative</governor>
            <dependent idx="36">that</dependent>
          </dep>
          <dep type="cop">
            <governor idx="40">alternative</governor>
            <dependent idx="37">are</dependent>
          </dep>
          <dep type="det">
            <governor idx="40">alternative</governor>
            <dependent idx="38">the</dependent>
          </dep>
          <dep type="amod">
            <governor idx="40">alternative</governor>
            <dependent idx="39">best</dependent>
          </dep>
          <dep type="rcmod">
            <governor idx="31">support</governor>
            <dependent idx="40">alternative</dependent>
          </dep>
          <dep type="prep">
            <governor idx="40">alternative</governor>
            <dependent idx="41">to</dependent>
          </dep>
          <dep type="nn">
            <governor idx="44">al-Assad</governor>
            <dependent idx="42">President</dependent>
          </dep>
          <dep type="nn">
            <governor idx="44">al-Assad</governor>
            <dependent idx="43">Bashar</dependent>
          </dep>
          <dep type="pobj">
            <governor idx="41">to</governor>
            <dependent idx="44">al-Assad</dependent>
          </dep>
        </dependencies>
        <dependencies type="collapsed-dependencies">
          <dep type="root">
            <governor idx="0">ROOT</governor>
            <dependent idx="21">said</dependent>
          </dep>
          <dep type="nn">
            <governor idx="6">Reuters</governor>
            <dependent idx="2">WEST</dependent>
          </dep>
          <dep type="nn">
            <governor idx="6">Reuters</governor>
            <dependent idx="3">POINT</dependent>
          </dep>
          <dep type="nn">
            <governor idx="6">Reuters</governor>
            <dependent idx="4">N.Y.</dependent>
          </dep>
          <dep type="nsubj">
            <governor idx="21">said</governor>
            <dependent idx="6">Reuters</dependent>
          </dep>
          <dep type="dep">
            <governor idx="21">said</governor>
            <dependent idx="9">In</dependent>
          </dep>
          <dep type="det">
            <governor idx="14">address</governor>
            <dependent idx="10">a</dependent>
          </dep>
          <dep type="amod">
            <governor idx="14">address</governor>
            <dependent idx="11">major</dependent>
          </dep>
          <dep type="amod">
            <governor idx="14">address</governor>
            <dependent idx="12">foreign</dependent>
          </dep>
          <dep type="nn">
            <governor idx="14">address</governor>
            <dependent idx="13">policy</dependent>
          </dep>
          <dep type="pobj">
            <governor idx="9">In</governor>
            <dependent idx="14">address</dependent>
          </dep>
          <dep type="prep_on">
            <governor idx="14">address</governor>
            <dependent idx="16">Wednesday</dependent>
          </dep>
          <dep type="nn">
            <governor idx="20">Obama</governor>
            <dependent idx="18">President</dependent>
          </dep>
          <dep type="nn">
            <governor idx="20">Obama</governor>
            <dependent idx="19">Barack</dependent>
          </dep>
          <dep type="nsubj">
            <governor idx="21">said</governor>
            <dependent idx="20">Obama</dependent>
          </dep>
          <dep type="nsubj">
            <governor idx="24">work</governor>
            <dependent idx="22">he</dependent>
          </dep>
          <dep type="aux">
            <governor idx="24">work</governor>
            <dependent idx="23">will</dependent>
          </dep>
          <dep type="ccomp">
            <governor idx="21">said</governor>
            <dependent idx="24">work</dependent>
          </dep>
          <dep type="prep_with">
            <governor idx="24">work</governor>
            <dependent idx="26">Congress</dependent>
          </dep>
          <dep type="aux">
            <governor idx="28">ramp</governor>
            <dependent idx="27">to</dependent>
          </dep>
          <dep type="xcomp">
            <governor idx="24">work</governor>
            <dependent idx="28">ramp</dependent>
          </dep>
          <dep type="prt">
            <governor idx="28">ramp</governor>
            <dependent idx="29">up</dependent>
          </dep>
          <dep type="nn">
            <governor idx="31">support</governor>
            <dependent idx="30">U.S.</dependent>
          </dep>
          <dep type="dobj">
            <governor idx="28">ramp</governor>
            <dependent idx="31">support</dependent>
          </dep>
          <dep type="amod">
            <governor idx="35">groups</governor>
            <dependent idx="33">Syrian</dependent>
          </dep>
          <dep type="nn">
            <governor idx="35">groups</governor>
            <dependent idx="34">opposition</dependent>
          </dep>
          <dep type="prep_for">
            <governor idx="31">support</governor>
            <dependent idx="35">groups</dependent>
          </dep>
          <dep type="nsubj">
            <governor idx="40">alternative</governor>
            <dependent idx="36">that</dependent>
          </dep>
          <dep type="cop">
            <governor idx="40">alternative</governor>
            <dependent idx="37">are</dependent>
          </dep>
          <dep type="det">
            <governor idx="40">alternative</governor>
            <dependent idx="38">the</dependent>
          </dep>
          <dep type="amod">
            <governor idx="40">alternative</governor>
            <dependent idx="39">best</dependent>
          </dep>
          <dep type="rcmod">
            <governor idx="31">support</governor>
            <dependent idx="40">alternative</dependent>
          </dep>
          <dep type="nn">
            <governor idx="44">al-Assad</governor>
            <dependent idx="42">President</dependent>
          </dep>
          <dep type="nn">
            <governor idx="44">al-Assad</governor>
            <dependent idx="43">Bashar</dependent>
          </dep>
          <dep type="prep_to">
            <governor idx="40">alternative</governor>
            <dependent idx="44">al-Assad</dependent>
          </dep>
        </dependencies>
        <dependencies type="collapsed-ccprocessed-dependencies">
          <dep type="root">
            <governor idx="0">ROOT</governor>
            <dependent idx="21">said</dependent>
          </dep>
          <dep type="nn">
            <governor idx="6">Reuters</governor>
            <dependent idx="2">WEST</dependent>
          </dep>
          <dep type="nn">
            <governor idx="6">Reuters</governor>
            <dependent idx="3">POINT</dependent>
          </dep>
          <dep type="nn">
            <governor idx="6">Reuters</governor>
            <dependent idx="4">N.Y.</dependent>
          </dep>
          <dep type="nsubj">
            <governor idx="21">said</governor>
            <dependent idx="6">Reuters</dependent>
          </dep>
          <dep type="dep">
            <governor idx="21">said</governor>
            <dependent idx="9">In</dependent>
          </dep>
          <dep type="det">
            <governor idx="14">address</governor>
            <dependent idx="10">a</dependent>
          </dep>
          <dep type="amod">
            <governor idx="14">address</governor>
            <dependent idx="11">major</dependent>
          </dep>
          <dep type="amod">
            <governor idx="14">address</governor>
            <dependent idx="12">foreign</dependent>
          </dep>
          <dep type="nn">
            <governor idx="14">address</governor>
            <dependent idx="13">policy</dependent>
          </dep>
          <dep type="pobj">
            <governor idx="9">In</governor>
            <dependent idx="14">address</dependent>
          </dep>
          <dep type="prep_on">
            <governor idx="14">address</governor>
            <dependent idx="16">Wednesday</dependent>
          </dep>
          <dep type="nn">
            <governor idx="20">Obama</governor>
            <dependent idx="18">President</dependent>
          </dep>
          <dep type="nn">
            <governor idx="20">Obama</governor>
            <dependent idx="19">Barack</dependent>
          </dep>
          <dep type="nsubj">
            <governor idx="21">said</governor>
            <dependent idx="20">Obama</dependent>
          </dep>
          <dep type="nsubj">
            <governor idx="24">work</governor>
            <dependent idx="22">he</dependent>
          </dep>
          <dep type="aux">
            <governor idx="24">work</governor>
            <dependent idx="23">will</dependent>
          </dep>
          <dep type="ccomp">
            <governor idx="21">said</governor>
            <dependent idx="24">work</dependent>
          </dep>
          <dep type="prep_with">
            <governor idx="24">work</governor>
            <dependent idx="26">Congress</dependent>
          </dep>
          <dep type="aux">
            <governor idx="28">ramp</governor>
            <dependent idx="27">to</dependent>
          </dep>
          <dep type="xcomp">
            <governor idx="24">work</governor>
            <dependent idx="28">ramp</dependent>
          </dep>
          <dep type="prt">
            <governor idx="28">ramp</governor>
            <dependent idx="29">up</dependent>
          </dep>
          <dep type="nn">
            <governor idx="31">support</governor>
            <dependent idx="30">U.S.</dependent>
          </dep>
          <dep type="dobj">
            <governor idx="28">ramp</governor>
            <dependent idx="31">support</dependent>
          </dep>
          <dep type="amod">
            <governor idx="35">groups</governor>
            <dependent idx="33">Syrian</dependent>
          </dep>
          <dep type="nn">
            <governor idx="35">groups</governor>
            <dependent idx="34">opposition</dependent>
          </dep>
          <dep type="prep_for">
            <governor idx="31">support</governor>
            <dependent idx="35">groups</dependent>
          </dep>
          <dep type="nsubj">
            <governor idx="40">alternative</governor>
            <dependent idx="36">that</dependent>
          </dep>
          <dep type="cop">
            <governor idx="40">alternative</governor>
            <dependent idx="37">are</dependent>
          </dep>
          <dep type="det">
            <governor idx="40">alternative</governor>
            <dependent idx="38">the</dependent>
          </dep>
          <dep type="amod">
            <governor idx="40">alternative</governor>
            <dependent idx="39">best</dependent>
          </dep>
          <dep type="rcmod">
            <governor idx="31">support</governor>
            <dependent idx="40">alternative</dependent>
          </dep>
          <dep type="nn">
            <governor idx="44">al-Assad</governor>
            <dependent idx="42">President</dependent>
          </dep>
          <dep type="nn">
            <governor idx="44">al-Assad</governor>
            <dependent idx="43">Bashar</dependent>
          </dep>
          <dep type="prep_to">
            <governor idx="40">alternative</governor>
            <dependent idx="44">al-Assad</dependent>
          </dep>
        </dependencies>
      </sentence>
      <sentence id="2">
        <tokens>
          <token id="1">
            <word>We</word>
            <lemma>we</lemma>
            <CharacterOffsetBegin>247</CharacterOffsetBegin>
            <CharacterOffsetEnd>249</CharacterOffsetEnd>
            <POS>PRP</POS>
            <NER>O</NER>
            <Speaker>PER1</Speaker>
          </token>
          <token id="2">
            <word>will</word>
            <lemma>will</lemma>
            <CharacterOffsetBegin>250</CharacterOffsetBegin>
            <CharacterOffsetEnd>254</CharacterOffsetEnd>
            <POS>MD</POS>
            <NER>O</NER>
            <Speaker>PER1</Speaker>
          </token>
          <token id="3">
            <word>step</word>
            <lemma>step</lemma>
            <CharacterOffsetBegin>255</CharacterOffsetBegin>
            <CharacterOffsetEnd>259</CharacterOffsetEnd>
            <POS>VB</POS>
            <NER>O</NER>
            <Speaker>PER1</Speaker>
          </token>
          <token id="4">
            <word>up</word>
            <lemma>up</lemma>
            <CharacterOffsetBegin>260</CharacterOffsetBegin>
            <CharacterOffsetEnd>262</CharacterOffsetEnd>
            <POS>RP</POS>
            <NER>O</NER>
            <Speaker>PER1</Speaker>
          </token>
          <token id="5">
            <word>our</word>
            <lemma>we</lemma>
            <CharacterOffsetBegin>263</CharacterOffsetBegin>
            <CharacterOffsetEnd>266</CharacterOffsetEnd>
            <POS>PRP$</POS>
            <NER>O</NER>
            <Speaker>PER1</Speaker>
          </token>
          <token id="6">
            <word>efforts</word>
            <lemma>effort</lemma>
            <CharacterOffsetBegin>267</CharacterOffsetBegin>
            <CharacterOffsetEnd>274</CharacterOffsetEnd>
            <POS>NNS</POS>
            <NER>O</NER>
            <Speaker>PER1</Speaker>
          </token>
          <token id="7">
            <word>to</word>
            <lemma>to</lemma>
            <CharacterOffsetBegin>275</CharacterOffsetBegin>
            <CharacterOffsetEnd>277</CharacterOffsetEnd>
            <POS>TO</POS>
            <NER>O</NER>
            <Speaker>PER1</Speaker>
          </token>
          <token id="8">
            <word>support</word>
            <lemma>support</lemma>
            <CharacterOffsetBegin>278</CharacterOffsetBegin>
            <CharacterOffsetEnd>285</CharacterOffsetEnd>
            <POS>VB</POS>
            <NER>O</NER>
            <Speaker>PER1</Speaker>
          </token>
          <token id="9">
            <word>Syria</word>
            <lemma>Syria</lemma>
            <CharacterOffsetBegin>286</CharacterOffsetBegin>
            <CharacterOffsetEnd>291</CharacterOffsetEnd>
            <POS>NNP</POS>
            <NER>LOCATION</NER>
            <Speaker>PER1</Speaker>
          </token>
          <token id="10">
            <word>'s</word>
            <lemma>'s</lemma>
            <CharacterOffsetBegin>291</CharacterOffsetBegin>
            <CharacterOffsetEnd>293</CharacterOffsetEnd>
            <POS>POS</POS>
            <NER>O</NER>
            <Speaker>PER1</Speaker>
          </token>
          <token id="11">
            <word>neighbors</word>
            <lemma>neighbor</lemma>
            <CharacterOffsetBegin>294</CharacterOffsetBegin>
            <CharacterOffsetEnd>303</CharacterOffsetEnd>
            <POS>NNS</POS>
            <NER>O</NER>
            <Speaker>PER1</Speaker>
          </token>
          <token id="12">
            <word>-</word>
            <lemma>-</lemma>
            <CharacterOffsetBegin>304</CharacterOffsetBegin>
            <CharacterOffsetEnd>305</CharacterOffsetEnd>
            <POS>:</POS>
            <NER>O</NER>
            <Speaker>PER1</Speaker>
          </token>
          <token id="13">
            <word>Jordan</word>
            <lemma>Jordan</lemma>
            <CharacterOffsetBegin>306</CharacterOffsetBegin>
            <CharacterOffsetEnd>312</CharacterOffsetEnd>
            <POS>NNP</POS>
            <NER>LOCATION</NER>
            <Speaker>PER1</Speaker>
          </token>
          <token id="14">
            <word>and</word>
            <lemma>and</lemma>
            <CharacterOffsetBegin>313</CharacterOffsetBegin>
            <CharacterOffsetEnd>316</CharacterOffsetEnd>
            <POS>CC</POS>
            <NER>O</NER>
            <Speaker>PER1</Speaker>
          </token>
          <token id="15">
            <word>Lebanon</word>
            <lemma>Lebanon</lemma>
            <CharacterOffsetBegin>317</CharacterOffsetBegin>
            <CharacterOffsetEnd>324</CharacterOffsetEnd>
            <POS>NNP</POS>
            <NER>LOCATION</NER>
            <Speaker>PER1</Speaker>
          </token>
          <token id="16">
            <word>,</word>
            <lemma>,</lemma>
            <CharacterOffsetBegin>324</CharacterOffsetBegin>
            <CharacterOffsetEnd>325</CharacterOffsetEnd>
            <POS>,</POS>
            <NER>O</NER>
            <Speaker>PER1</Speaker>
          </token>
          <token id="17">
            <word>Turkey</word>
            <lemma>Turkey</lemma>
            <CharacterOffsetBegin>326</CharacterOffsetBegin>
            <CharacterOffsetEnd>332</CharacterOffsetEnd>
            <POS>NNP</POS>
            <NER>LOCATION</NER>
            <Speaker>PER1</Speaker>
          </token>
          <token id="18">
            <word>and</word>
            <lemma>and</lemma>
            <CharacterOffsetBegin>333</CharacterOffsetBegin>
            <CharacterOffsetEnd>336</CharacterOffsetEnd>
            <POS>CC</POS>
            <NER>O</NER>
            <Speaker>PER1</Speaker>
          </token>
          <token id="19">
            <word>Iraq</word>
            <lemma>Iraq</lemma>
            <CharacterOffsetBegin>337</CharacterOffsetBegin>
            <CharacterOffsetEnd>341</CharacterOffsetEnd>
            <POS>NNP</POS>
            <NER>LOCATION</NER>
            <Speaker>PER1</Speaker>
          </token>
          <token id="20">
            <word>-</word>
            <lemma>-</lemma>
            <CharacterOffsetBegin>342</CharacterOffsetBegin>
            <CharacterOffsetEnd>343</CharacterOffsetEnd>
            <POS>:</POS>
            <NER>O</NER>
            <Speaker>PER1</Speaker>
          </token>
          <token id="21">
            <word>as</word>
            <lemma>as</lemma>
            <CharacterOffsetBegin>344</CharacterOffsetBegin>
            <CharacterOffsetEnd>346</CharacterOffsetEnd>
            <POS>IN</POS>
            <NER>O</NER>
            <Speaker>PER1</Speaker>
          </token>
          <token id="22">
            <word>they</word>
            <lemma>they</lemma>
            <CharacterOffsetBegin>347</CharacterOffsetBegin>
            <CharacterOffsetEnd>351</CharacterOffsetEnd>
            <POS>PRP</POS>
            <NER>O</NER>
            <Speaker>PER1</Speaker>
          </token>
          <token id="23">
            <word>host</word>
            <lemma>host</lemma>
            <CharacterOffsetBegin>352</CharacterOffsetBegin>
            <CharacterOffsetEnd>356</CharacterOffsetEnd>
            <POS>VBP</POS>
            <NER>O</NER>
            <Speaker>PER1</Speaker>
          </token>
          <token id="24">
            <word>refugees</word>
            <lemma>refugee</lemma>
            <CharacterOffsetBegin>357</CharacterOffsetBegin>
            <CharacterOffsetEnd>365</CharacterOffsetEnd>
            <POS>NNS</POS>
            <NER>O</NER>
            <Speaker>PER1</Speaker>
          </token>
          <token id="25">
            <word>,</word>
            <lemma>,</lemma>
            <CharacterOffsetBegin>365</CharacterOffsetBegin>
            <CharacterOffsetEnd>366</CharacterOffsetEnd>
            <POS>,</POS>
            <NER>O</NER>
            <Speaker>PER1</Speaker>
          </token>
          <token id="26">
            <word>and</word>
            <lemma>and</lemma>
            <CharacterOffsetBegin>367</CharacterOffsetBegin>
            <CharacterOffsetEnd>370</CharacterOffsetEnd>
            <POS>CC</POS>
            <NER>O</NER>
            <Speaker>PER1</Speaker>
          </token>
          <token id="27">
            <word>confront</word>
            <lemma>confront</lemma>
            <CharacterOffsetBegin>371</CharacterOffsetBegin>
            <CharacterOffsetEnd>379</CharacterOffsetEnd>
            <POS>VB</POS>
            <NER>O</NER>
            <Speaker>PER1</Speaker>
          </token>
          <token id="28">
            <word>terrorists</word>
            <lemma>terrorist</lemma>
            <CharacterOffsetBegin>380</CharacterOffsetBegin>
            <CharacterOffsetEnd>390</CharacterOffsetEnd>
            <POS>NNS</POS>
            <NER>O</NER>
            <Speaker>PER1</Speaker>
          </token>
          <token id="29">
            <word>working</word>
            <lemma>work</lemma>
            <CharacterOffsetBegin>391</CharacterOffsetBegin>
            <CharacterOffsetEnd>398</CharacterOffsetEnd>
            <POS>VBG</POS>
            <NER>O</NER>
            <Speaker>PER1</Speaker>
          </token>
          <token id="30">
            <word>across</word>
            <lemma>across</lemma>
            <CharacterOffsetBegin>399</CharacterOffsetBegin>
            <CharacterOffsetEnd>405</CharacterOffsetEnd>
            <POS>IN</POS>
            <NER>O</NER>
            <Speaker>PER1</Speaker>
          </token>
          <token id="31">
            <word>Syrian</word>
            <lemma>syrian</lemma>
            <CharacterOffsetBegin>406</CharacterOffsetBegin>
            <CharacterOffsetEnd>412</CharacterOffsetEnd>
            <POS>JJ</POS>
            <NER>MISC</NER>
            <Speaker>PER1</Speaker>
          </token>
          <token id="32">
            <word>borders</word>
            <lemma>border</lemma>
            <CharacterOffsetBegin>413</CharacterOffsetBegin>
            <CharacterOffsetEnd>420</CharacterOffsetEnd>
            <POS>NNS</POS>
            <NER>O</NER>
            <Speaker>PER1</Speaker>
          </token>
          <token id="33">
            <word>,</word>
            <lemma>,</lemma>
            <CharacterOffsetBegin>420</CharacterOffsetBegin>
            <CharacterOffsetEnd>421</CharacterOffsetEnd>
            <POS>,</POS>
            <NER>O</NER>
            <Speaker>PER1</Speaker>
          </token>
          <token id="34">
            <word>Obama</word>
            <lemma>Obama</lemma>
            <CharacterOffsetBegin>422</CharacterOffsetBegin>
            <CharacterOffsetEnd>427</CharacterOffsetEnd>
            <POS>NNP</POS>
            <NER>PERSON</NER>
            <Speaker>PER1</Speaker>
          </token>
          <token id="35">
            <word>said</word>
            <lemma>say</lemma>
            <CharacterOffsetBegin>428</CharacterOffsetBegin>
            <CharacterOffsetEnd>432</CharacterOffsetEnd>
            <POS>VBD</POS>
            <NER>O</NER>
            <Speaker>PER1</Speaker>
          </token>
          <token id="36">
            <word>in</word>
            <lemma>in</lemma>
            <CharacterOffsetBegin>433</CharacterOffsetBegin>
            <CharacterOffsetEnd>435</CharacterOffsetEnd>
            <POS>IN</POS>
            <NER>O</NER>
            <Speaker>PER1</Speaker>
          </token>
          <token id="37">
            <word>his</word>
            <lemma>he</lemma>
            <CharacterOffsetBegin>436</CharacterOffsetBegin>
            <CharacterOffsetEnd>439</CharacterOffsetEnd>
            <POS>PRP$</POS>
            <NER>O</NER>
            <Speaker>PER1</Speaker>
          </token>
          <token id="38">
            <word>prepared</word>
            <lemma>prepared</lemma>
            <CharacterOffsetBegin>440</CharacterOffsetBegin>
            <CharacterOffsetEnd>448</CharacterOffsetEnd>
            <POS>JJ</POS>
            <NER>O</NER>
            <Speaker>PER1</Speaker>
          </token>
          <token id="39">
            <word>remarks</word>
            <lemma>remark</lemma>
            <CharacterOffsetBegin>449</CharacterOffsetBegin>
            <CharacterOffsetEnd>456</CharacterOffsetEnd>
            <POS>NNS</POS>
            <NER>O</NER>
            <Speaker>PER1</Speaker>
          </token>
          <token id="40">
            <word>.</word>
            <lemma>.</lemma>
            <CharacterOffsetBegin>456</CharacterOffsetBegin>
            <CharacterOffsetEnd>457</CharacterOffsetEnd>
            <POS>.</POS>
            <NER>O</NER>
            <Speaker>PER1</Speaker>
          </token>
        </tokens>
        <parse>(ROOT (S (S (NP (PRP We)) (VP (MD will) (VP (VB step) (PRT (RP up)) (NP (PRP$ our) (NNS efforts)) (S (VP (TO to) (VP (VP (VB support) (NP (NP (NP (NNP Syria) (POS 's)) (NNS neighbors)) (PRN (: -) (NP (NP (NNP Jordan)) (CC and) (NP (NNP Lebanon) (, ,) (NNP Turkey) (CC and) (NNP Iraq))) (: -))) (SBAR (IN as) (S (NP (PRP they)) (VP (VBP host) (NP (NNS refugees)))))) (, ,) (CC and) (VP (VB confront) (NP (NP (NNS terrorists)) (VP (VBG working) (PP (IN across) (NP (JJ Syrian) (NNS borders)))))))))))) (, ,) (NP (NNP Obama)) (VP (VBD said) (PP (IN in) (NP (PRP$ his) (JJ prepared) (NNS remarks)))) (. .))) </parse>
        <dependencies type="basic-dependencies">
          <dep type="root">
            <governor idx="0">ROOT</governor>
            <dependent idx="35">said</dependent>
          </dep>
          <dep type="nsubj">
            <governor idx="3">step</governor>
            <dependent idx="1">We</dependent>
          </dep>
          <dep type="aux">
            <governor idx="3">step</governor>
            <dependent idx="2">will</dependent>
          </dep>
          <dep type="ccomp">
            <governor idx="35">said</governor>
            <dependent idx="3">step</dependent>
          </dep>
          <dep type="prt">
            <governor idx="3">step</governor>
            <dependent idx="4">up</dependent>
          </dep>
          <dep type="poss">
            <governor idx="6">efforts</governor>
            <dependent idx="5">our</dependent>
          </dep>
          <dep type="dobj">
            <governor idx="3">step</governor>
            <dependent idx="6">efforts</dependent>
          </dep>
          <dep type="aux">
            <governor idx="8">support</governor>
            <dependent idx="7">to</dependent>
          </dep>
          <dep type="xcomp">
            <governor idx="3">step</governor>
            <dependent idx="8">support</dependent>
          </dep>
          <dep type="poss">
            <governor idx="11">neighbors</governor>
            <dependent idx="9">Syria</dependent>
          </dep>
          <dep type="possessive">
            <governor idx="9">Syria</governor>
            <dependent idx="10">'s</dependent>
          </dep>
          <dep type="dobj">
            <governor idx="8">support</governor>
            <dependent idx="11">neighbors</dependent>
          </dep>
          <dep type="dep">
            <governor idx="11">neighbors</governor>
            <dependent idx="13">Jordan</dependent>
          </dep>
          <dep type="cc">
            <governor idx="13">Jordan</governor>
            <dependent idx="14">and</dependent>
          </dep>
          <dep type="conj">
            <governor idx="13">Jordan</governor>
            <dependent idx="15">Lebanon</dependent>
          </dep>
          <dep type="conj">
            <governor idx="15">Lebanon</governor>
            <dependent idx="17">Turkey</dependent>
          </dep>
          <dep type="cc">
            <governor idx="15">Lebanon</governor>
            <dependent idx="18">and</dependent>
          </dep>
          <dep type="conj">
            <governor idx="15">Lebanon</governor>
            <dependent idx="19">Iraq</dependent>
          </dep>
          <dep type="mark">
            <governor idx="23">host</governor>
            <dependent idx="21">as</dependent>
          </dep>
          <dep type="nsubj">
            <governor idx="23">host</governor>
            <dependent idx="22">they</dependent>
          </dep>
          <dep type="advcl">
            <governor idx="8">support</governor>
            <dependent idx="23">host</dependent>
          </dep>
          <dep type="dobj">
            <governor idx="23">host</governor>
            <dependent idx="24">refugees</dependent>
          </dep>
          <dep type="cc">
            <governor idx="8">support</governor>
            <dependent idx="26">and</dependent>
          </dep>
          <dep type="conj">
            <governor idx="8">support</governor>
            <dependent idx="27">confront</dependent>
          </dep>
          <dep type="dobj">
            <governor idx="27">confront</governor>
            <dependent idx="28">terrorists</dependent>
          </dep>
          <dep type="vmod">
            <governor idx="28">terrorists</governor>
            <dependent idx="29">working</dependent>
          </dep>
          <dep type="prep">
            <governor idx="29">working</governor>
            <dependent idx="30">across</dependent>
          </dep>
          <dep type="amod">
            <governor idx="32">borders</governor>
            <dependent idx="31">Syrian</dependent>
          </dep>
          <dep type="pobj">
            <governor idx="30">across</governor>
            <dependent idx="32">borders</dependent>
          </dep>
          <dep type="nsubj">
            <governor idx="35">said</governor>
            <dependent idx="34">Obama</dependent>
          </dep>
          <dep type="prep">
            <governor idx="35">said</governor>
            <dependent idx="36">in</dependent>
          </dep>
          <dep type="poss">
            <governor idx="39">remarks</governor>
            <dependent idx="37">his</dependent>
          </dep>
          <dep type="amod">
            <governor idx="39">remarks</governor>
            <dependent idx="38">prepared</dependent>
          </dep>
          <dep type="pobj">
            <governor idx="36">in</governor>
            <dependent idx="39">remarks</dependent>
          </dep>
        </dependencies>
        <dependencies type="collapsed-dependencies">
          <dep type="root">
            <governor idx="0">ROOT</governor>
            <dependent idx="35">said</dependent>
          </dep>
          <dep type="nsubj">
            <governor idx="3">step</governor>
            <dependent idx="1">We</dependent>
          </dep>
          <dep type="aux">
            <governor idx="3">step</governor>
            <dependent idx="2">will</dependent>
          </dep>
          <dep type="ccomp">
            <governor idx="35">said</governor>
            <dependent idx="3">step</dependent>
          </dep>
          <dep type="prt">
            <governor idx="3">step</governor>
            <dependent idx="4">up</dependent>
          </dep>
          <dep type="poss">
            <governor idx="6">efforts</governor>
            <dependent idx="5">our</dependent>
          </dep>
          <dep type="dobj">
            <governor idx="3">step</governor>
            <dependent idx="6">efforts</dependent>
          </dep>
          <dep type="aux">
            <governor idx="8">support</governor>
            <dependent idx="7">to</dependent>
          </dep>
          <dep type="xcomp">
            <governor idx="3">step</governor>
            <dependent idx="8">support</dependent>
          </dep>
          <dep type="poss">
            <governor idx="11">neighbors</governor>
            <dependent idx="9">Syria</dependent>
          </dep>
          <dep type="dobj">
            <governor idx="8">support</governor>
            <dependent idx="11">neighbors</dependent>
          </dep>
          <dep type="dep">
            <governor idx="11">neighbors</governor>
            <dependent idx="13">Jordan</dependent>
          </dep>
          <dep type="conj_and">
            <governor idx="13">Jordan</governor>
            <dependent idx="15">Lebanon</dependent>
          </dep>
          <dep type="conj_and">
            <governor idx="15">Lebanon</governor>
            <dependent idx="17">Turkey</dependent>
          </dep>
          <dep type="conj_and">
            <governor idx="15">Lebanon</governor>
            <dependent idx="19">Iraq</dependent>
          </dep>
          <dep type="mark">
            <governor idx="23">host</governor>
            <dependent idx="21">as</dependent>
          </dep>
          <dep type="nsubj">
            <governor idx="23">host</governor>
            <dependent idx="22">they</dependent>
          </dep>
          <dep type="advcl">
            <governor idx="8">support</governor>
            <dependent idx="23">host</dependent>
          </dep>
          <dep type="dobj">
            <governor idx="23">host</governor>
            <dependent idx="24">refugees</dependent>
          </dep>
          <dep type="conj_and">
            <governor idx="8">support</governor>
            <dependent idx="27">confront</dependent>
          </dep>
          <dep type="dobj">
            <governor idx="27">confront</governor>
            <dependent idx="28">terrorists</dependent>
          </dep>
          <dep type="vmod">
            <governor idx="28">terrorists</governor>
            <dependent idx="29">working</dependent>
          </dep>
          <dep type="amod">
            <governor idx="32">borders</governor>
            <dependent idx="31">Syrian</dependent>
          </dep>
          <dep type="prep_across">
            <governor idx="29">working</governor>
            <dependent idx="32">borders</dependent>
          </dep>
          <dep type="nsubj">
            <governor idx="35">said</governor>
            <dependent idx="34">Obama</dependent>
          </dep>
          <dep type="poss">
            <governor idx="39">remarks</governor>
            <dependent idx="37">his</dependent>
          </dep>
          <dep type="amod">
            <governor idx="39">remarks</governor>
            <dependent idx="38">prepared</dependent>
          </dep>
          <dep type="prep_in">
            <governor idx="35">said</governor>
            <dependent idx="39">remarks</dependent>
          </dep>
        </dependencies>
        <dependencies type="collapsed-ccprocessed-dependencies">
          <dep type="root">
            <governor idx="0">ROOT</governor>
            <dependent idx="35">said</dependent>
          </dep>
          <dep type="nsubj">
            <governor idx="3">step</governor>
            <dependent idx="1">We</dependent>
          </dep>
          <dep type="aux">
            <governor idx="3">step</governor>
            <dependent idx="2">will</dependent>
          </dep>
          <dep type="ccomp">
            <governor idx="35">said</governor>
            <dependent idx="3">step</dependent>
          </dep>
          <dep type="prt">
            <governor idx="3">step</governor>
            <dependent idx="4">up</dependent>
          </dep>
          <dep type="poss">
            <governor idx="6">efforts</governor>
            <dependent idx="5">our</dependent>
          </dep>
          <dep type="dobj">
            <governor idx="3">step</governor>
            <dependent idx="6">efforts</dependent>
          </dep>
          <dep type="aux">
            <governor idx="8">support</governor>
            <dependent idx="7">to</dependent>
          </dep>
          <dep type="xcomp">
            <governor idx="3">step</governor>
            <dependent idx="8">support</dependent>
          </dep>
          <dep type="poss">
            <governor idx="11">neighbors</governor>
            <dependent idx="9">Syria</dependent>
          </dep>
          <dep type="dobj">
            <governor idx="8">support</governor>
            <dependent idx="11">neighbors</dependent>
          </dep>
          <dep type="dep">
            <governor idx="11">neighbors</governor>
            <dependent idx="13">Jordan</dependent>
          </dep>
          <dep type="dep">
            <governor idx="11">neighbors</governor>
            <dependent idx="15">Lebanon</dependent>
          </dep>
          <dep type="conj_and">
            <governor idx="13">Jordan</governor>
            <dependent idx="15">Lebanon</dependent>
          </dep>
          <dep type="conj_and">
            <governor idx="13">Jordan</governor>
            <dependent idx="17">Turkey</dependent>
          </dep>
          <dep type="conj_and">
            <governor idx="15">Lebanon</governor>
            <dependent idx="17">Turkey</dependent>
          </dep>
          <dep type="conj_and">
            <governor idx="13">Jordan</governor>
            <dependent idx="19">Iraq</dependent>
          </dep>
          <dep type="conj_and">
            <governor idx="15">Lebanon</governor>
            <dependent idx="19">Iraq</dependent>
          </dep>
          <dep type="mark">
            <governor idx="23">host</governor>
            <dependent idx="21">as</dependent>
          </dep>
          <dep type="nsubj">
            <governor idx="23">host</governor>
            <dependent idx="22">they</dependent>
          </dep>
          <dep type="advcl">
            <governor idx="8">support</governor>
            <dependent idx="23">host</dependent>
          </dep>
          <dep type="dobj">
            <governor idx="23">host</governor>
            <dependent idx="24">refugees</dependent>
          </dep>
          <dep type="xcomp">
            <governor idx="3">step</governor>
            <dependent idx="27">confront</dependent>
          </dep>
          <dep type="conj_and">
            <governor idx="8">support</governor>
            <dependent idx="27">confront</dependent>
          </dep>
          <dep type="dobj">
            <governor idx="27">confront</governor>
            <dependent idx="28">terrorists</dependent>
          </dep>
          <dep type="vmod">
            <governor idx="28">terrorists</governor>
            <dependent idx="29">working</dependent>
          </dep>
          <dep type="amod">
            <governor idx="32">borders</governor>
            <dependent idx="31">Syrian</dependent>
          </dep>
          <dep type="prep_across">
            <governor idx="29">working</governor>
            <dependent idx="32">borders</dependent>
          </dep>
          <dep type="nsubj">
            <governor idx="35">said</governor>
            <dependent idx="34">Obama</dependent>
          </dep>
          <dep type="poss">
            <governor idx="39">remarks</governor>
            <dependent idx="37">his</dependent>
          </dep>
          <dep type="amod">
            <governor idx="39">remarks</governor>
            <dependent idx="38">prepared</dependent>
          </dep>
          <dep type="prep_in">
            <governor idx="35">said</governor>
            <dependent idx="39">remarks</dependent>
          </dep>
        </dependencies>
      </sentence>
      <sentence id="3">
        <tokens>
          <token id="1">
            <word>-LRB-</word>
            <lemma>-lrb-</lemma>
            <CharacterOffsetBegin>460</CharacterOffsetBegin>
            <CharacterOffsetEnd>461</CharacterOffsetEnd>
            <POS>-LRB-</POS>
            <NER>O</NER>
            <Speaker>PER1</Speaker>
          </token>
          <token id="2">
            <word>Reporting</word>
            <lemma>Reporting</lemma>
            <CharacterOffsetBegin>461</CharacterOffsetBegin>
            <CharacterOffsetEnd>470</CharacterOffsetEnd>
            <POS>NNP</POS>
            <NER>O</NER>
            <Speaker>PER1</Speaker>
          </token>
          <token id="3">
            <word>by</word>
            <lemma>by</lemma>
            <CharacterOffsetBegin>471</CharacterOffsetBegin>
            <CharacterOffsetEnd>473</CharacterOffsetEnd>
            <POS>IN</POS>
            <NER>O</NER>
            <Speaker>PER1</Speaker>
          </token>
          <token id="4">
            <word>Jeff</word>
            <lemma>Jeff</lemma>
            <CharacterOffsetBegin>474</CharacterOffsetBegin>
            <CharacterOffsetEnd>478</CharacterOffsetEnd>
            <POS>NNP</POS>
            <NER>PERSON</NER>
            <Speaker>PER1</Speaker>
          </token>
          <token id="5">
            <word>Mason</word>
            <lemma>Mason</lemma>
            <CharacterOffsetBegin>479</CharacterOffsetBegin>
            <CharacterOffsetEnd>484</CharacterOffsetEnd>
            <POS>NNP</POS>
            <NER>PERSON</NER>
            <Speaker>PER1</Speaker>
          </token>
          <token id="6">
            <word>,</word>
            <lemma>,</lemma>
            <CharacterOffsetBegin>484</CharacterOffsetBegin>
            <CharacterOffsetEnd>485</CharacterOffsetEnd>
            <POS>,</POS>
            <NER>O</NER>
            <Speaker>PER1</Speaker>
          </token>
          <token id="7">
            <word>Steve</word>
            <lemma>Steve</lemma>
            <CharacterOffsetBegin>486</CharacterOffsetBegin>
            <CharacterOffsetEnd>491</CharacterOffsetEnd>
            <POS>NNP</POS>
            <NER>PERSON</NER>
            <Speaker>PER1</Speaker>
          </token>
          <token id="8">
            <word>Holland</word>
            <lemma>Holland</lemma>
            <CharacterOffsetBegin>492</CharacterOffsetBegin>
            <CharacterOffsetEnd>499</CharacterOffsetEnd>
            <POS>NNP</POS>
            <NER>PERSON</NER>
            <Speaker>PER1</Speaker>
          </token>
          <token id="9">
            <word>,</word>
            <lemma>,</lemma>
            <CharacterOffsetBegin>499</CharacterOffsetBegin>
            <CharacterOffsetEnd>500</CharacterOffsetEnd>
            <POS>,</POS>
            <NER>O</NER>
            <Speaker>PER1</Speaker>
          </token>
          <token id="10">
            <word>Roberta</word>
            <lemma>Roberta</lemma>
            <CharacterOffsetBegin>501</CharacterOffsetBegin>
            <CharacterOffsetEnd>508</CharacterOffsetEnd>
            <POS>NNP</POS>
            <NER>PERSON</NER>
            <Speaker>PER1</Speaker>
          </token>
          <token id="11">
            <word>Rampton</word>
            <lemma>Rampton</lemma>
            <CharacterOffsetBegin>509</CharacterOffsetBegin>
            <CharacterOffsetEnd>516</CharacterOffsetEnd>
            <POS>NNP</POS>
            <NER>PERSON</NER>
            <Speaker>PER1</Speaker>
          </token>
          <token id="12">
            <word>;</word>
            <lemma>;</lemma>
            <CharacterOffsetBegin>516</CharacterOffsetBegin>
            <CharacterOffsetEnd>517</CharacterOffsetEnd>
            <POS>:</POS>
            <NER>O</NER>
            <Speaker>PER1</Speaker>
          </token>
          <token id="13">
            <word>Editing</word>
            <lemma>editing</lemma>
            <CharacterOffsetBegin>518</CharacterOffsetBegin>
            <CharacterOffsetEnd>525</CharacterOffsetEnd>
            <POS>NN</POS>
            <NER>O</NER>
            <Speaker>PER1</Speaker>
          </token>
          <token id="14">
            <word>by</word>
            <lemma>by</lemma>
            <CharacterOffsetBegin>526</CharacterOffsetBegin>
            <CharacterOffsetEnd>528</CharacterOffsetEnd>
            <POS>IN</POS>
            <NER>O</NER>
            <Speaker>PER1</Speaker>
          </token>
          <token id="15">
            <word>Doina</word>
            <lemma>Doina</lemma>
            <CharacterOffsetBegin>529</CharacterOffsetBegin>
            <CharacterOffsetEnd>534</CharacterOffsetEnd>
            <POS>NNP</POS>
            <NER>PERSON</NER>
            <Speaker>PER1</Speaker>
          </token>
          <token id="16">
            <word>Chiacu</word>
            <lemma>Chiacu</lemma>
            <CharacterOffsetBegin>535</CharacterOffsetBegin>
            <CharacterOffsetEnd>541</CharacterOffsetEnd>
            <POS>NNP</POS>
            <NER>PERSON</NER>
            <Speaker>PER1</Speaker>
          </token>
          <token id="17">
            <word>-RRB-</word>
            <lemma>-rrb-</lemma>
            <CharacterOffsetBegin>541</CharacterOffsetBegin>
            <CharacterOffsetEnd>542</CharacterOffsetEnd>
            <POS>-RRB-</POS>
            <NER>O</NER>
            <Speaker>PER1</Speaker>
          </token>
          <token id="18">
            <word>''</word>
            <lemma>''</lemma>
            <CharacterOffsetBegin>542</CharacterOffsetBegin>
            <CharacterOffsetEnd>543</CharacterOffsetEnd>
            <POS>''</POS>
            <NER>O</NER>
            <Speaker>PER0</Speaker>
          </token>
        </tokens>
        <parse>(ROOT (NP (-LRB- -LRB-) (NP (NNP Reporting)) (PP (IN by) (NP (NP (NNP Jeff) (NNP Mason)) (, ,) (NP (NNP Steve) (NNP Holland)) (, ,) (NP (NP (NNP Roberta)) (NP (NP (NNP Rampton)) (: ;) (NP (NP (NN Editing)) (PP (IN by) (NP (NNP Doina) (NNP Chiacu)))) (-RRB- -RRB-))) ('' ''))))) </parse>
        <dependencies type="basic-dependencies">
          <dep type="root">
            <governor idx="0">ROOT</governor>
            <dependent idx="2">Reporting</dependent>
          </dep>
          <dep type="prep">
            <governor idx="2">Reporting</governor>
            <dependent idx="3">by</dependent>
          </dep>
          <dep type="nn">
            <governor idx="5">Mason</governor>
            <dependent idx="4">Jeff</dependent>
          </dep>
          <dep type="pobj">
            <governor idx="3">by</governor>
            <dependent idx="5">Mason</dependent>
          </dep>
          <dep type="nn">
            <governor idx="8">Holland</governor>
            <dependent idx="7">Steve</dependent>
          </dep>
          <dep type="appos">
            <governor idx="5">Mason</governor>
            <dependent idx="8">Holland</dependent>
          </dep>
          <dep type="appos">
            <governor idx="5">Mason</governor>
            <dependent idx="10">Roberta</dependent>
          </dep>
          <dep type="dep">
            <governor idx="10">Roberta</governor>
            <dependent idx="11">Rampton</dependent>
          </dep>
          <dep type="dep">
            <governor idx="11">Rampton</governor>
            <dependent idx="13">Editing</dependent>
          </dep>
          <dep type="prep">
            <governor idx="13">Editing</governor>
            <dependent idx="14">by</dependent>
          </dep>
          <dep type="nn">
            <governor idx="16">Chiacu</governor>
            <dependent idx="15">Doina</dependent>
          </dep>
          <dep type="pobj">
            <governor idx="14">by</governor>
            <dependent idx="16">Chiacu</dependent>
          </dep>
        </dependencies>
        <dependencies type="collapsed-dependencies">
          <dep type="root">
            <governor idx="0">ROOT</governor>
            <dependent idx="2">Reporting</dependent>
          </dep>
          <dep type="nn">
            <governor idx="5">Mason</governor>
            <dependent idx="4">Jeff</dependent>
          </dep>
          <dep type="prep_by">
            <governor idx="2">Reporting</governor>
            <dependent idx="5">Mason</dependent>
          </dep>
          <dep type="nn">
            <governor idx="8">Holland</governor>
            <dependent idx="7">Steve</dependent>
          </dep>
          <dep type="appos">
            <governor idx="5">Mason</governor>
            <dependent idx="8">Holland</dependent>
          </dep>
          <dep type="appos">
            <governor idx="5">Mason</governor>
            <dependent idx="10">Roberta</dependent>
          </dep>
          <dep type="dep">
            <governor idx="10">Roberta</governor>
            <dependent idx="11">Rampton</dependent>
          </dep>
          <dep type="dep">
            <governor idx="11">Rampton</governor>
            <dependent idx="13">Editing</dependent>
          </dep>
          <dep type="nn">
            <governor idx="16">Chiacu</governor>
            <dependent idx="15">Doina</dependent>
          </dep>
          <dep type="prep_by">
            <governor idx="13">Editing</governor>
            <dependent idx="16">Chiacu</dependent>
          </dep>
        </dependencies>
        <dependencies type="collapsed-ccprocessed-dependencies">
          <dep type="root">
            <governor idx="0">ROOT</governor>
            <dependent idx="2">Reporting</dependent>
          </dep>
          <dep type="nn">
            <governor idx="5">Mason</governor>
            <dependent idx="4">Jeff</dependent>
          </dep>
          <dep type="prep_by">
            <governor idx="2">Reporting</governor>
            <dependent idx="5">Mason</dependent>
          </dep>
          <dep type="nn">
            <governor idx="8">Holland</governor>
            <dependent idx="7">Steve</dependent>
          </dep>
          <dep type="appos">
            <governor idx="5">Mason</governor>
            <dependent idx="8">Holland</dependent>
          </dep>
          <dep type="appos">
            <governor idx="5">Mason</governor>
            <dependent idx="10">Roberta</dependent>
          </dep>
          <dep type="dep">
            <governor idx="10">Roberta</governor>
            <dependent idx="11">Rampton</dependent>
          </dep>
          <dep type="dep">
            <governor idx="11">Rampton</governor>
            <dependent idx="13">Editing</dependent>
          </dep>
          <dep type="nn">
            <governor idx="16">Chiacu</governor>
            <dependent idx="15">Doina</dependent>
          </dep>
          <dep type="prep_by">
            <governor idx="13">Editing</governor>
            <dependent idx="16">Chiacu</dependent>
          </dep>
        </dependencies>
      </sentence>
    </sentences>
    <coreference>
      <coreference>
        <mention representative="true">
          <sentence>1</sentence>
          <start>18</start>
          <end>21</end>
          <head>20</head>
          <text>President Barack Obama</text>
        </mention>
        <mention>
          <sentence>1</sentence>
          <start>22</start>
          <end>23</end>
          <head>22</head>
          <text>he</text>
        </mention>
        <mention>
          <sentence>2</sentence>
          <start>34</start>
          <end>35</end>
          <head>34</head>
          <text>Obama</text>
        </mention>
        <mention>
          <sentence>2</sentence>
          <start>37</start>
          <end>38</end>
          <head>37</head>
          <text>his</text>
        </mention>
      </coreference>
      <coreference>
        <mention representative="true">
          <sentence>2</sentence>
          <start>1</start>
          <end>2</end>
          <head>1</head>
          <text>We</text>
        </mention>
        <mention>
          <sentence>2</sentence>
          <start>5</start>
          <end>6</end>
          <head>5</head>
          <text>our</text>
        </mention>
      </coreference>
      <coreference>
        <mention representative="true">
          <sentence>2</sentence>
          <start>9</start>
          <end>21</end>
          <head>11</head>
          <text>Syria 's neighbors - Jordan and Lebanon , Turkey and Iraq -</text>
        </mention>
        <mention>
          <sentence>2</sentence>
          <start>22</start>
          <end>23</end>
          <head>22</head>
          <text>they</text>
        </mention>
      </coreference>
    </coreference>
  </document>
</root>
